{
  "ar": [null,
    "اصنع خطاً يمر بنقطتين",
    "اصنع خطاً عن طريق طي نقطة واحدة إلى أخرى",
    "اصنع خطاً عن طريق طي خط واحد على آخر",
    "اصنع خطاً يمر عبر نقطة واحدة ويجعل خطاً واحداً فوق نفسه",
    "اصنع خطاً يمر بالنقطة الأولى ويجعل النقطة الثانية على الخط",
    "اصنع خطاً يجلب النقطة الأولى إلى الخط الأول والنقطة الثانية إلى الخط الثاني",
    "اصنع خطاً يجلب نقطة إلى خط ويجعل خط ثاني فوق نفسه"
  ],
  "de": [null,
    "Falte eine Linie durch zwei Punkte",
    "Falte zwei Punkte aufeinander",
    "Falte zwei Linien aufeinander",
    "Falte eine Linie auf sich selbst, falte dabei durch einen Punkt",
    "Falte einen Punkt auf eine Linie, falte dabei durch einen anderen Punkt",
    "Falte einen Punkt auf eine Linie und einen weiteren Punkt auf eine weitere Linie",
    "Falte einen Punkt auf eine Linie und eine weitere Linie in sich selbst zusammen"
  ],
  "en": [null,
    "fold a line through two points",
    "fold two points together",
    "fold two lines together",
    "fold a line on top of itself, creasing through a point",
    "fold a point to a line, creasing through another point",
    "fold a point to a line and another point to another line",
    "fold a point to a line and another line onto itself"
  ],
  "es": [null,
    "dobla una línea entre dos puntos",
    "dobla dos puntos juntos",
    "dobla y une dos líneas",
    "dobla una línea sobre sí misma, doblándola hacia un punto",
    "dobla un punto hasta una línea, doblándola a través de otro punto",
    "dobla un punto hacia una línea y otro punto hacia otra línea",
    "dobla un punto hacia una línea y otra línea sobre sí misma"
  ],
  "fr":[null,
    "créez un pli passant par deux points",
    "pliez pour superposer deux points",
    "pliez pour superposer deux lignes",
    "rabattez une ligne sur elle-même à l'aide d'un pli qui passe par un point",
    "rabattez un point sur une ligne à l'aide d'un pli qui passe par un autre point",
    "rabattez un point sur une ligne et un autre point sur une autre ligne",
    "rabattez un point sur une ligne et une autre ligne sur elle-même"
  ],
  "hi": [null,
    "एक क्रीज़ बनाएँ जो दो स्थानों से गुजरता है",
    "एक स्थान को दूसरे स्थान पर मोड़कर एक क्रीज़ बनाएँ",
    "एक रेखा पर दूसरी रेखा को मोड़कर क्रीज़ बनाएँ",
    "एक क्रीज़ बनाएँ जो एक स्थान से गुजरता है और एक रेखा को स्वयं के ऊपर ले आता है",
    "एक क्रीज़ बनाएँ जो पहले स्थान से गुजरता है और दूसरे स्थान को रेखा पर ले आता है",
    "एक क्रीज़ बनाएँ जो पहले स्थान को पहली रेखा पर और दूसरे स्थान को दूसरी रेखा पर ले आता है",
    "एक क्रीज़ बनाएँ जो एक स्थान को एक रेखा पर ले आता है और दूसरी रेखा को स्वयं के ऊपर ले आता है"
  ],
  "jp": [null,
    "2点に沿って折り目を付けます",
    "2点を合わせて折ります",
    "2つの線を合わせて折ります",
    "点を通過させ、既にある線に沿って折ります",
    "点を線沿いに合わせ別の点を通過させ折ります",
    "線に向かって点を折り、同時にもう一方の線に向かってもう一方の点を折ります",
    "線に向かって点を折り、同時に別の線をその上に折ります"
  ],
  "ko": [null,
    "두 점을 통과하는 선으로 접으세요",
    "두 점을 함께 접으세요",
    "두 선을 함께 접으세요",
    "그 위에 선을 접으면서 점을 통과하게 접으세요",
    "점을 선으로 접으면서, 다른 점을 지나게 접으세요",
    "점을 선으로 접고 다른 점을 다른 선으로 접으세요",
    "점을 선으로 접고 다른 선을 그 위에 접으세요"
  ],
  "ms": [null,
    "lipat garisan melalui dua titik",
    "lipat dua titik bersama",
    "lipat dua garisan bersama",
    "lipat satu garisan di atasnya sendiri, melipat melalui satu titik",
    "lipat satu titik ke garisan, melipat melalui titik lain",
    "lipat satu titik ke garisan dan satu lagi titik ke garisan lain",
    "lipat satu titik ke garisan dan satu lagi garisan di atasnya sendiri"
  ],
  "pt": [null,
    "dobre uma linha entre dois pontos",
    "dobre os dois pontos para uni-los",
    "dobre as duas linhas para uni-las",
    "dobre uma linha sobre si mesma, criando uma dobra ao longo de um ponto",
    "dobre um ponto até uma linha, criando uma dobra ao longo de outro ponto",
    "dobre um ponto até uma linha e outro ponto até outra linha",
    "dobre um ponto até uma linha e outra linha sobre si mesma"
  ],
  "ru": [null,
    "сложите линию через две точки",
    "сложите две точки вместе",
    "сложите две линии вместе",
    "сверните линию сверху себя, сгибая через точку",
    "сложите точку в линию, сгибая через другую точку",
    "сложите точку в линию и другую точку в другую линию",
    "сложите точку в линию и другую линию на себя"
  ],
  "tr": [null,
    "iki noktadan geçen bir çizgi boyunca katla",
    "iki noktayı birbirine katla",
    "iki çizgiyi birbirine katla",
    "bir noktadan kıvırarak kendi üzerindeki bir çizgi boyunca katla",
    "başka bir noktadan kıvırarak bir noktayı bir çizgiye katla",
    "bir noktayı bir çizgiye ve başka bir noktayı başka bir çizgiye katla",
    "bir noktayı bir çizgiye ve başka bir çizgiyi kendi üzerine katla"
  ],
  "vi": [null,
    "tạo một nếp gấp đi qua hai điểm",
    "tạo nếp gấp bằng cách gấp một điểm này sang điểm khác",
    "tạo nếp gấp bằng cách gấp một đường lên một đường khác",
    "tạo một nếp gấp đi qua một điểm và đưa một đường lên trên chính nó",
    "tạo một nếp gấp đi qua điểm đầu tiên và đưa điểm thứ hai lên đường thẳng",
    "tạo một nếp gấp mang điểm đầu tiên đến đường đầu tiên và điểm thứ hai cho đường thứ hai",
    "tạo một nếp gấp mang lại một điểm cho một đường và đưa một đường thứ hai lên trên chính nó"
  ],
  "zh": [null,
    "通過兩點折一條線",
    "將兩點折疊起來",
    "將兩條線折疊在一起",
    "通過一個點折疊一條線在自身上面",
    "將一個點，通過另一個點折疊成一條線，",
    "將一個點折疊為一條線，再將另一個點折疊到另一條線",
    "將一個點折疊成一條線，另一條線折疊到它自身上"
  ]
}
